llmatch_bm25/__init__.py
llmatch_bm25/main.py
llmatch_bm25/prompts.py
llmatch_bm25-2025.12.21101341.dist-info/METADATA
llmatch_bm25-2025.12.21101341.dist-info/WHEEL
llmatch_bm25-2025.12.21101341.dist-info/top_level.txt
llmatch_bm25-2025.12.21101341.dist-info/RECORD
