Metadata-Version: 2.4
Name: llmatch-bm25
Version: 2025.12.21101341
Summary: The new package transforms a user’s plain‑text search phrase into a structured, BM25‑ranked list of PostgreSQL search results. It takes the query text as input, forwards it to an LLM that rewrites the
Author-email: llmatch-bm25 <hi@eugene.plus>
License: MIT
Project-URL: Homepage, https://github.com/chigwell/llmatch-bm25
Requires-Python: >=3.9
Requires-Dist: langchain-llm7>=0.0.0
Requires-Dist: llmatch-messages>=0.0.0
Requires-Dist: langchain-core>=0.3.0
